data_diff_viewer/__init__.py
data_diff_viewer/diff_summary.py
data_diff_viewer/package.py
data_diff_viewer/py.typed
data_diff_viewer/templates/diff_report.html
data_diff_viewer/utils.py
data_diff_viewer-0.4.0.dist-info/LICENSE
data_diff_viewer-0.4.0.dist-info/METADATA
data_diff_viewer-0.4.0.dist-info/WHEEL
data_diff_viewer-0.4.0.dist-info/RECORD
