Metadata-Version: 2.1
Name: data-diff-viewer
Version: 0.4.0
Summary: Generate HTML reports to visualize the results of data-diff with bigquery-frame and spark-frame.
Home-page: https://github.com/FurcyPin/data-diff-viewer
Author: Furcy Pin
Author-email: pin.furcy@gmail.com
Requires-Python: >=3.10,<3.15
Classifier: Programming Language :: Python :: 3
Classifier: Programming Language :: Python :: 3.10
Classifier: Programming Language :: Python :: 3.11
Classifier: Programming Language :: Python :: 3.12
Requires-Dist: duckdb (>=1.4.3,<1.5.0)
Project-URL: Repository, https://github.com/FurcyPin/data-diff-viewer
